eridu/__init__.py
eridu/cli/__init__.py
eridu/cli/main.py
eridu/etl/__init__.py
eridu/etl/compare.py
eridu/etl/report.py
eridu/train/__init__.py
eridu/train/callbacks.py
eridu/train/dataset.py
eridu/train/fine_tune_sbert.py
eridu/train/utils.py
eridu-0.1.5.dist-info/LICENSE
eridu-0.1.5.dist-info/METADATA
eridu-0.1.5.dist-info/WHEEL
eridu-0.1.5.dist-info/entry_points.txt
eridu-0.1.5.dist-info/RECORD
