Metadata-Version: 2.3
Name: eridu
Version: 0.1.5
Summary: Deep fuzzy matching people and company names for multilingual entity resolution using representation learning
License: Apache 2.0
Keywords: entity resolution,fuzzy matching,representation learning,deep learning,machine learning,graph neural networks,transformers,sentence transformers,pandas,numpy,pyspark
Author: Russell Jurney, Graphlet AI,
Author-email: rjurney@graphlet.ai
Requires-Python: >=3.12,<4.0
Classifier: Development Status :: 4 - Beta
Classifier: Environment :: Console
Classifier: Intended Audience :: Developers
Classifier: Intended Audience :: Science/Research
Classifier: License :: OSI Approved :: Apache Software License
Classifier: License :: Other/Proprietary License
Classifier: Natural Language :: English
Classifier: Operating System :: OS Independent
Classifier: Programming Language :: Python
Classifier: Programming Language :: Python :: 3
Classifier: Programming Language :: Python :: 3.12
Classifier: Programming Language :: Python :: 3.13
Classifier: Topic :: Database :: Database Engines/Servers
Classifier: Topic :: Scientific/Engineering :: Artificial Intelligence
Classifier: Topic :: Scientific/Engineering :: Information Analysis
Classifier: Topic :: Software Development :: Libraries :: Python Modules
Classifier: Topic :: Text Processing :: Linguistic
Requires-Dist: accelerate (>=1.6.0,<2.0.0)
Requires-Dist: click (>=8.1.7,<9.0.0)
Requires-Dist: datasets (>=3.5.1,<4.0.0)
Requires-Dist: ipython (>=9.0.2,<10.0.0)
Requires-Dist: jupyter (>=1.1.1,<2.0.0)
Requires-Dist: notebook (>=7.3.3,<8.0.0)
Requires-Dist: numpy (>=2.2,<3.0)
Requires-Dist: pandas (>=2.2.3,<3.0.0)
Requires-Dist: pyarrow (>=19.0.1,<20.0.0)
Requires-Dist: pyspark (>=3.5.5,<4.0.0)
Requires-Dist: requests (>=2.32.3,<3.0.0)
Requires-Dist: seaborn (>=0.13.2,<0.14.0)
Requires-Dist: sentence-transformers[torch] (>=3.4.1,<4.0.0)
Requires-Dist: tqdm (>=4.67.1,<5.0.0)
Requires-Dist: transformers[torch] (>=4.51.3,<5.0.0)
Requires-Dist: wandb (>=0.19.10,<0.20.0)
Project-URL: Bug Tracker, https://github.com/Graphlet-AI/eridu/issues
Project-URL: Company, https://graphlet.ai
Project-URL: Code Repository, https://github.com/Graphlet-AI/eridu
Project-URL: Documentation, https://github.com/Graphlet-AI/eridu
Project-URL: Homepage, https://github.com/Graphlet-AI/eridu
Project-URL: HuggingFace Hub, https://huggingface.co/Graphlet-AI/eridu
Project-URL: Repository, https://github.com/Graphlet-AI/eridu
